talkito/__init__.py
talkito/__main__.py
talkito/__version__.py
talkito/api.py
talkito/asr.py
talkito/cli.py
talkito/clients.py
talkito/comms.py
talkito/core.py
talkito/logs.py
talkito/mcp.py
talkito/models.py
talkito/profiles.py
talkito/state.py
talkito/templates.py
talkito/tts.py
talkito/update.py
talkito/voices.py
talkito-1.0.0.dist-info/licenses/LICENSE
talkito-1.0.0.dist-info/METADATA
talkito-1.0.0.dist-info/WHEEL
talkito-1.0.0.dist-info/entry_points.txt
talkito-1.0.0.dist-info/top_level.txt
talkito-1.0.0.dist-info/RECORD
