Metadata-Version: 2.4
Name: talkito
Version: 1.0.0
Summary: Universal TTS wrapper and voice interaction library for command-line programs
Home-page: https://github.com/robdmac/talkito
Author: Robert Macrae
License: AGPL-3.0-or-later
Project-URL: Homepage, https://github.com/robdmac/talkito
Project-URL: Documentation, https://github.com/robdmac/talkito/blob/main/README.md
Project-URL: Repository, https://github.com/robdmac/talkito
Project-URL: Issues, https://github.com/robdmac/talkito/issues
Keywords: tts,text-to-speech,asr,speech-recognition,voice,terminal,cli,command-line,accessibility,ai,llm,claude,chatgpt,voice-assistant
Classifier: Development Status :: 4 - Beta
Classifier: Intended Audience :: Developers
Classifier: Topic :: Software Development :: Libraries :: Python Modules
Classifier: Topic :: Multimedia :: Sound/Audio :: Speech
Classifier: Topic :: System :: Shells
Classifier: Topic :: Utilities
Classifier: License :: OSI Approved :: GNU Affero General Public License v3 or later (AGPLv3+)
Classifier: Programming Language :: Python :: 3
Classifier: Programming Language :: Python :: 3.10
Classifier: Programming Language :: Python :: 3.11
Classifier: Programming Language :: Python :: 3.12
Classifier: Programming Language :: Python :: 3.13
Classifier: Operating System :: MacOS :: MacOS X
Classifier: Operating System :: POSIX :: Linux
Classifier: Environment :: Console
Requires-Python: >=3.10
License-File: LICENSE
Requires-Dist: SpeechRecognition>=3.8.1
Requires-Dist: pyaudio>=0.2.11
Requires-Dist: openai>=1.0.0
Requires-Dist: boto3>=1.26.0
Requires-Dist: amazon-transcribe>=0.6.0
Requires-Dist: azure-cognitiveservices-speech>=1.24.0
Requires-Dist: google-cloud-texttospeech>=2.14.0
Requires-Dist: google-cloud-speech>=2.20.0
Requires-Dist: elevenlabs>=0.2.0
Requires-Dist: assemblyai>=0.5.0
Requires-Dist: deepgram-sdk>=2.0.0
Requires-Dist: twilio>=8.0.0
Requires-Dist: slack-sdk>=3.19.0
Requires-Dist: flask>=2.0.0
Requires-Dist: waitress>=2.0.0
Requires-Dist: kokoro>=0.9.4
Requires-Dist: soundfile>=0.12.0
Requires-Dist: numpy<2.0
Requires-Dist: fastmcp>=0.1.0
Dynamic: home-page
Dynamic: license-file
Dynamic: requires-python
